python_refactor_tool_box/__init__.py
python_refactor_tool_box/python_refactor_helper.py
python_refactor_tool_box/snake_case.py
python_refactor_tool_box/source_directory.py
python_refactor_tool_box/source_file.py
python_refactor_tool_box-0.0.0.3.dist-info/LICENSE.txt
python_refactor_tool_box-0.0.0.3.dist-info/METADATA
python_refactor_tool_box-0.0.0.3.dist-info/WHEEL
python_refactor_tool_box-0.0.0.3.dist-info/top_level.txt
python_refactor_tool_box-0.0.0.3.dist-info/RECORD
