Metadata-Version: 2.1
Name: python_refactor_tool_box
Version: 0.0.0.3
Summary: A set of tools helping to refactor python code
Home-page: https://github.com/Rinzler78/PythonRefactorToolbox
Author: Rinzler78
Author-email: Borisleclere@gmail.com
License: Apache-2.0
Project-URL: Documentation, https://pyscaffold.org/
Platform: any
Classifier: Development Status :: 4 - Beta
Classifier: Programming Language :: Python
License-File: LICENSE.txt
Requires-Dist: autopep8
Requires-Dist: astor
Requires-Dist: importlib-metadata ; python_version < "3.8"
Provides-Extra: testing
Requires-Dist: setuptools ; extra == 'testing'
Requires-Dist: pytest ; extra == 'testing'
Requires-Dist: pytest-cov ; extra == 'testing'
